cli_tool/__init__.py
cli_tool/asyncioTest.py
cli_tool/click_demo.py
cli_tool/importtest.py
cli_tool/test.py
chris_cliTool-1.0.0.dist-info/LICENSE
chris_cliTool-1.0.0.dist-info/METADATA
chris_cliTool-1.0.0.dist-info/WHEEL
chris_cliTool-1.0.0.dist-info/entry_points.txt
chris_cliTool-1.0.0.dist-info/top_level.txt
chris_cliTool-1.0.0.dist-info/RECORD
