Metadata-Version: 2.1
Name: chris-cliTool
Version: 1.0.0
Summary: s3 push
Home-page: https://test.com
Author: Chris
Author-email: huangyf0991@gmail.com
License: MIT
Platform: UNKNOWN
Classifier: Development Status :: 5 - Production/Stable
Classifier: Intended Audience :: Developers
Classifier: Operating System :: Unix
Classifier: Operating System :: POSIX
Classifier: Programming Language :: Python
Classifier: Programming Language :: Python :: 3.8
Classifier: Topic :: Utilities
License-File: LICENSE
Requires-Dist: click
Requires-Dist: requests
Requires-Dist: boto3
